pypika_orm/__init__.py
pypika_orm/dialects.py
pypika_orm/fields.py
pypika_orm/manager.py
pypika_orm/model.py
pypika_orm/query.py
pypika_orm-0.0.15.dist-info/METADATA
pypika_orm-0.0.15.dist-info/WHEEL
pypika_orm-0.0.15.dist-info/top_level.txt
pypika_orm-0.0.15.dist-info/RECORD
